mcp_web_crawler_client/.dockerignore
mcp_web_crawler_client/__init__.py
mcp_web_crawler_client/mcp_client.py
mcp_web_crawler_client/mcp_client_cli.py
mcp_web_crawler_client/standalone_mcp_client.py
mcp_web_crawler_client-1.0.1.dist-info/METADATA
mcp_web_crawler_client-1.0.1.dist-info/WHEEL
mcp_web_crawler_client-1.0.1.dist-info/entry_points.txt
mcp_web_crawler_client-1.0.1.dist-info/RECORD
