Metadata-Version: 2.4
Name: mcp-web-crawler-client
Version: 1.0.1
Summary: A Python MCP (Model Context Protocol) client for connecting to remote web crawler servers.
Project-URL: Homepage, https://github.com/jquad-group/mcp-web-crawler-client
Project-URL: Repository, https://github.com/jquad-group/mcp-web-crawler-client.git
Project-URL: Documentation, https://github.com/jquad-group/mcp-web-crawler-client/blob/main/README.md
Project-URL: Issues, https://github.com/jquad-group/mcp-web-crawler-client/issues
Author-email: JQuad OHG <info@jquad.de>
License: MIT
Keywords: client,http,mcp,model-context-protocol,web-crawler
Classifier: Development Status :: 5 - Production/Stable
Classifier: Intended Audience :: Developers
Classifier: License :: OSI Approved :: MIT License
Classifier: Programming Language :: Python :: 3
Classifier: Programming Language :: Python :: 3.11
Classifier: Programming Language :: Python :: 3.12
Classifier: Programming Language :: Python :: 3.13
Classifier: Topic :: Communications
Classifier: Topic :: Internet :: WWW/HTTP :: Browsers
Classifier: Topic :: Software Development :: Libraries :: Python Modules
Requires-Python: >=3.11
Requires-Dist: aiohttp>=3.9.0
Requires-Dist: pydantic>=2.0.0
Provides-Extra: dev
Requires-Dist: pytest-asyncio>=0.23.0; extra == 'dev'
Requires-Dist: pytest>=8.0.0; extra == 'dev'
